nullbr/__init__.py
nullbr/__main__.py
nullbr/cli.py
nullbr/models/__init__.py
nullbr/models/base.py
nullbr/models/collection.py
nullbr/models/movie.py
nullbr/models/search.py
nullbr/models/tv.py
nullbr-1.0.7.dist-info/METADATA
nullbr-1.0.7.dist-info/WHEEL
nullbr-1.0.7.dist-info/entry_points.txt
nullbr-1.0.7.dist-info/licenses/LICENSE
nullbr-1.0.7.dist-info/RECORD
